lektor_index_pages-1.1.0.dist-info/METADATA
lektor_index_pages-1.1.0.dist-info/WHEEL
lektor_index_pages-1.1.0.dist-info/entry_points.txt
lektor_index_pages-1.1.0.dist-info/licenses/LICENSE
lektor_index_pages/__init__.py
lektor_index_pages/buildprog.py
lektor_index_pages/config.py
lektor_index_pages/indexmodel.py
lektor_index_pages/plugin.py
lektor_index_pages/sourceobj.py
tests/__init__.py
tests/conftest.py
tests/demo-site/Test Project.lektorproject
tests/demo-site/assets/static/style.css
tests/demo-site/configs/index-pages.ini
tests/demo-site/content/blog/contents.lr
tests/demo-site/content/blog/first-post/contents.lr
tests/demo-site/content/blog/second-post/contents.lr
tests/demo-site/content/contents.lr
tests/demo-site/models/blog-post.ini
tests/demo-site/models/blog.ini
tests/demo-site/models/page.ini
tests/demo-site/templates/blog-post.html
tests/demo-site/templates/blog.html
tests/demo-site/templates/layout.html
tests/demo-site/templates/macros/blog-index.html
tests/demo-site/templates/macros/blog.html
tests/demo-site/templates/macros/pagination.html
tests/demo-site/templates/month-index.html
tests/demo-site/templates/page.html
tests/demo-site/templates/year-index.html
tests/test_buildprog.py
tests/test_config.py
tests/test_functional.py
tests/test_indexmodel.py
tests/test_plugin.py
tests/test_sourceobj.py
lektor_index_pages-1.1.0.dist-info/RECORD
