Metadata-Version: 2.1
Name: lektor-index-pages
Version: 1.1.0
Summary: Lektor plugin to generate blog-like index pages
Keywords: Lektor plugin blog index
Author-Email: Jeff Dairiki <dairiki@dairiki.org>
License: Copyright © 2020 Geoffrey T. Dairiki
Classifier: Development Status :: 5 - Production/Stable
Classifier: Environment :: Plugins
Classifier: Environment :: Web Environment
Classifier: Framework :: Lektor
Classifier: Intended Audience :: Developers
Classifier: License :: OSI Approved :: MIT License
Classifier: Programming Language :: Python :: 3
Classifier: Programming Language :: Python :: 3.7
Classifier: Programming Language :: Python :: 3.8
Classifier: Programming Language :: Python :: 3.9
Classifier: Programming Language :: Python :: 3.10
Classifier: Programming Language :: Python :: 3.11
Classifier: Topic :: Text Processing :: Indexing
Project-URL: Homepage, https://github.com/dairiki/lektor-index-pages
Project-URL: Documentation, https://lektor-index-pages.readthedocs.io/en/latest/
Requires-Python: >=3.7
Requires-Dist: importlib_metadata; python_version < "3.10"
Requires-Dist: more-itertools
Requires-Dist: lektorlib>=1.2.1
Requires-Dist: jinja2~=3.0
Requires-Dist: typing_extensions; python_version < "3.8"
